propylen/__init__.py
propylen/__main__.py
propylen/cli/__init__.py
propylen/functionality/__init__.py
propylen-0.4.4.dist-info/entry_points.txt
propylen-0.4.4.dist-info/WHEEL
propylen-0.4.4.dist-info/METADATA
propylen-0.4.4.dist-info/RECORD
