Metadata-Version: 2.1
Name: propylen
Version: 0.4.4
Summary: Python project scaffolding generator
Home-page: https://github.com/petereon/propylen
License: MIT
Keywords: project,template,generator,scaffolding
Author: Petereon
Author-email: pvyboch1@gmail.com
Requires-Python: >=3.7,<4.0
Classifier: License :: OSI Approved :: MIT License
Classifier: Natural Language :: English
Classifier: Programming Language :: Python :: 3
Classifier: Programming Language :: Python :: 3.10
Classifier: Programming Language :: Python :: 3.7
Classifier: Programming Language :: Python :: 3.8
Classifier: Programming Language :: Python :: 3.9
Requires-Dist: cleo (>=0.8.1,<0.9.0)
Requires-Dist: click (>=8.0.4,<9.0.0)
Requires-Dist: emoji (>=1.6.3,<2.0.0)
Requires-Dist: pipenv (>=2022.1.8,<2023.0.0)
Requires-Dist: poetry (>=1.1.13,<2.0.0)
Requires-Dist: toml (>=0.10.2,<0.11.0)
Project-URL: Repository, https://github.com/petereon/propylen
